gptorch/__init__.py
gptorch/ekernels.py
gptorch/functions.py
gptorch/kernels.py
gptorch/likelihoods.py
gptorch/mean_functions.py
gptorch/model.py
gptorch/param.py
gptorch/settings.py
gptorch/util.py
gptorch/models/__init__.py
gptorch/models/base.py
gptorch/models/gplvm.py
gptorch/models/gpr.py
gptorch/models/sparse_gpr.py
test/__init__.py
test/test_base.py
test/test_examples.py
test/test_functions.py
test/test_kernels.py
test/test_likelihoods.py
test/test_mean_functions.py
test/test_model.py
test/test_param.py
test/test_util.py
test/util.py
test/test_models/__init__.py
test/test_models/common.py
test/test_models/test_base.py
test/test_models/test_gpr.py
test/test_models/test_sparse_gpr.py
gptorch-0.3.2.dist-info/LICENSE
gptorch-0.3.2.dist-info/METADATA
gptorch-0.3.2.dist-info/WHEEL
gptorch-0.3.2.dist-info/top_level.txt
gptorch-0.3.2.dist-info/RECORD
