Metadata-Version: 2.1
Name: gptorch
Version: 0.3.2
Summary: gptorch - a Gaussian process toolbox built on PyTorch
Home-page: https://github.com/cics-nd/gptorch
Author: Yinhao Zhu, Steven Atkinson
Author-email: yzhu10@nd.edu, satkinso@nd.edu
License: UNKNOWN
Platform: UNKNOWN
License-File: LICENSE
Requires-Dist: numpy (>=1.10)
Requires-Dist: scipy (>=0.18)
Requires-Dist: matplotlib (>=2.1.2)
Requires-Dist: scikit-learn (>=0.19.1)
Requires-Dist: torch
Requires-Dist: pytest (>=3.5.0)
Requires-Dist: graphviz (>=0.9)
Requires-Dist: jupyter
